stabilizer/__init__.py
stabilizer/dataset.py
stabilizer/llrd.py
stabilizer/model.py
stabilizer/reinitialize.py
stabilizer/reproducibility.py
stabilizer/trainer.py
stabilizer-1.0.2.dist-info/LICENSE
stabilizer-1.0.2.dist-info/METADATA
stabilizer-1.0.2.dist-info/WHEEL
stabilizer-1.0.2.dist-info/top_level.txt
stabilizer-1.0.2.dist-info/RECORD
