Metadata-Version: 2.1
Name: stabilizer
Version: 1.0.2
Summary: Stabilize and achieve excellent performance with transformers
Home-page: https://github.com/flowerpot-ai/stabilizer
Author: flowerpot-ai
Author-email: vignesh.sbaskaran@gmail.com
License: UNKNOWN
Platform: UNKNOWN
Classifier: Programming Language :: Python :: 3
Classifier: License :: OSI Approved :: MIT License
Classifier: Operating System :: OS Independent
Requires-Python: >=3.7
Requires-Dist: torch (==1.9.0)
Requires-Dist: pandas (==1.3.1)
Requires-Dist: scikit-learn (==0.24.2)
Requires-Dist: transformers (==4.10.0)
